Bootstrap2YonghuZhinanWaiBowang/README.md
Bootstrap2YonghuZhinanWaiBowang/__init__.py
Bootstrap2YonghuZhinanWaiBowang/__main__.py
Bootstrap2YonghuZhinanWaiBowang/file.epub
Bootstrap2YonghuZhinanWaiBowang/index.html
Bootstrap2YonghuZhinanWaiBowang/css/__init__.py
Bootstrap2YonghuZhinanWaiBowang/css/annotations.css
Bootstrap2YonghuZhinanWaiBowang/css/main.css
Bootstrap2YonghuZhinanWaiBowang/css/normalize.css
Bootstrap2YonghuZhinanWaiBowang/css/popup.css
Bootstrap2YonghuZhinanWaiBowang/font/__init__.py
Bootstrap2YonghuZhinanWaiBowang/font/fontello.eot
Bootstrap2YonghuZhinanWaiBowang/font/fontello.svg
Bootstrap2YonghuZhinanWaiBowang/font/fontello.ttf
Bootstrap2YonghuZhinanWaiBowang/font/fontello.woff
Bootstrap2YonghuZhinanWaiBowang/img/__init__.py
Bootstrap2YonghuZhinanWaiBowang/img/annotator-glyph-sprite.png
Bootstrap2YonghuZhinanWaiBowang/img/annotator-icon-sprite.png
Bootstrap2YonghuZhinanWaiBowang/img/apple-touch-icon.png
Bootstrap2YonghuZhinanWaiBowang/img/cancelfullscreen.png
Bootstrap2YonghuZhinanWaiBowang/img/close.png
Bootstrap2YonghuZhinanWaiBowang/img/fullscreen.png
Bootstrap2YonghuZhinanWaiBowang/img/loader.gif
Bootstrap2YonghuZhinanWaiBowang/img/menu-icon.png
Bootstrap2YonghuZhinanWaiBowang/img/save.png
Bootstrap2YonghuZhinanWaiBowang/img/saved.png
Bootstrap2YonghuZhinanWaiBowang/img/settings-s.png
Bootstrap2YonghuZhinanWaiBowang/img/settings.png
Bootstrap2YonghuZhinanWaiBowang/img/star.png
Bootstrap2YonghuZhinanWaiBowang/js/__init__.py
Bootstrap2YonghuZhinanWaiBowang/js/epub.js
Bootstrap2YonghuZhinanWaiBowang/js/epub.min.js
Bootstrap2YonghuZhinanWaiBowang/js/epub.min.map
Bootstrap2YonghuZhinanWaiBowang/js/hooks.min.js
Bootstrap2YonghuZhinanWaiBowang/js/hooks.min.map
Bootstrap2YonghuZhinanWaiBowang/js/reader.js
Bootstrap2YonghuZhinanWaiBowang/js/reader.js.map
Bootstrap2YonghuZhinanWaiBowang/js/reader.min.js
Bootstrap2YonghuZhinanWaiBowang/js/reader.min.map
Bootstrap2YonghuZhinanWaiBowang/js/hooks/__init__.py
bootstrap2_yonghu_zhinan_wai_bowang-2024.3.4.0.dist-info/METADATA
bootstrap2_yonghu_zhinan_wai_bowang-2024.3.4.0.dist-info/WHEEL
bootstrap2_yonghu_zhinan_wai_bowang-2024.3.4.0.dist-info/entry_points.txt
bootstrap2_yonghu_zhinan_wai_bowang-2024.3.4.0.dist-info/top_level.txt
bootstrap2_yonghu_zhinan_wai_bowang-2024.3.4.0.dist-info/RECORD
